binance/__init__.py
binance/api.py
binance/error.py
binance/version.py
binance/lib/__init__.py
binance/lib/enums.py
binance/lib/utils.py
binance/spot/__init__.py
binance/spot/apis.py
binance/spot/blvt.py
binance/spot/bswap.py
binance/spot/data_stream.py
binance/spot/futures.py
binance/spot/margin.py
binance/spot/mining.py
binance/spot/savings.py
binance/spot/sub_account.py
binance/spot/wallet.py
binance/websocket/__init__.py
binance/websocket/binance_client_factory.py
binance/websocket/binance_client_protocol.py
binance/websocket/binance_socket_manager.py
binance/websocket/websocket_client.py
binance/websocket/spot/__init__.py
binance/websocket/spot/websocket_client.py
binance_connector_python-0.6.0.dist-info/LICENSE.md
binance_connector_python-0.6.0.dist-info/METADATA
binance_connector_python-0.6.0.dist-info/WHEEL
binance_connector_python-0.6.0.dist-info/top_level.txt
binance_connector_python-0.6.0.dist-info/RECORD
