Metadata-Version: 2.1
Name: binance-connector-python
Version: 0.6.0
Summary: This is a thin library that working as a connector to the Binance public API.
Home-page: https://github.com/binance-exchange/binance-connector-python
Author: Jeremy
License: MIT
Keywords: Binance,Public API
Platform: UNKNOWN
Classifier: Intended Audience :: Developers
Classifier: Intended Audience :: Financial and Insurance Industry
Classifier: License :: OSI Approved :: MIT License
Classifier: Programming Language :: Python :: 3.6
Classifier: Programming Language :: Python :: 3.7
Classifier: Programming Language :: Python :: 3.8
Classifier: Programming Language :: Python :: 3.9
Requires-Python: >=3.6
